python_mads/__init__.py
python_mads/add.py
python_mads/divide.py
python_mads/multiply.py
python_mads/subtract.py
python_mads-0.0.1.dist-info/METADATA
python_mads-0.0.1.dist-info/WHEEL
python_mads-0.0.1.dist-info/top_level.txt
python_mads-0.0.1.dist-info/RECORD
